tritium_pipeline/__init__.py
tritium_pipeline/algebra/__init__.py
tritium_pipeline/algebra/types/__init__.py
tritium_pipeline/algebra/types/log.py
tritium_pipeline/algebra/types/pipeline.py
tritium_pipeline/algebra/types/processor.py
tritium_pipeline/distribution/__init__.py
tritium_pipeline/distribution/pool.py
tritium_pipeline/log/__init__.py
tritium_pipeline/log/analyse.py
tritium_pipeline/log/default.py
tritium_pipeline-0.4.0.dist-info/WHEEL
tritium_pipeline-0.4.0.dist-info/METADATA
tritium_pipeline-0.4.0.dist-info/RECORD
