Metadata-Version: 2.1
Name: tritium-pipeline
Version: 0.4.0
Summary: Log based job pipeline tool
License: GPLv3
Author: voidpointercast
Author-email: patrick.daniel.gress@gmail.com
Requires-Python: >=3.10,<4.0
Classifier: License :: Other/Proprietary License
Classifier: Programming Language :: Python :: 3
Classifier: Programming Language :: Python :: 3.10
Requires-Dist: pydantic (>=1.9.0,<2.0.0)
Requires-Dist: toolz (>=0.11.2,<0.12.0)
